{"idVendor": "0x046d Logitech, Inc.", "idProduct": "0x0892 C920 HD Pro Webcam", "iProduct": "2 HD Pro Webcam C920", "bcdUSB": "2.00", "formats": [{"resolutions": [{"w": 640, "h": 480, "resolution": "640x480", "humanbitrate": "24Mb/s-147Mb/s", "minbps": 24576000, "maxbps": 147456000, "fps": [30, 24, 20, 15, 10, 8, 5]}, {"w": 160, "h": 90, "resolution": "160x90", "humanbitrate": "1152Kb/s-6912Kb/s", "minbps": 1152000, "maxbps": 6912000, "fps": [30, 24, 20, 15, 10, 8, 5]}, {"w": 160, "h": 120, "resolution": "160x120", "humanbitrate": "1536Kb/s-9216Kb/s", "minbps": 1536000, "maxbps": 9216000, "fps": [30, 24, 20, 15, 10, 8, 5]}, {"w": 176, "h": 144, "resolution": "176x144", "humanbitrate": "2027Kb/s-12Mb/s", "minbps": 2027520, "maxbps": 12165120, "fps": [30, 24, 20, 15, 10, 8, 5]}, {"w": 320, "h": 180, "resolution": "320x180", "humanbitrate": "4608Kb/s-27Mb/s", "minbps": 4608000, "maxbps": 27648000, "fps": [30, 24, 20, 15, 10, 8, 5]}, {"w": 320, "h": 240, "resolution": "320x240", "humanbitrate": "6144Kb/s-36Mb/s", "minbps": 6144000, "maxbps": 36864000, "fps": [30, 24, 20, 15, 10, 8, 5]}, {"w": 352, "h": 288, "resolution": "352x288", "humanbitrate": "8110Kb/s-48Mb/s", "minbps": 8110080, "maxbps": 48660480, "fps": [30, 24, 20, 15, 10, 8, 5]}, {"w": 432, "h": 240, "resolution": "432x240", "humanbitrate": "8294Kb/s-49Mb/s", "minbps": 8294400, "maxbps": 49766400, "fps": [30, 24, 20, 15, 10, 8, 5]}, {"w": 640, "h": 360, "resolution": "640x360", "humanbitrate": "18Mb/s-110Mb/s", "minbps": 18432000, "maxbps": 110592000, "fps": [30, 24, 20, 15, 10, 8, 5]}, {"w": 800, "h": 448, "resolution": "800x448", "humanbitrate": "28Mb/s-172Mb/s", "minbps": 28672000, "maxbps": 172032000, "fps": [30, 24, 20, 15, 10, 8, 5]}, {"w": 800, "h": 600, "resolution": "800x600", "humanbitrate": "38Mb/s-184Mb/s", "minbps": 38400000, "maxbps": 184320000, "fps": [24, 20, 15, 10, 8, 5]}, {"w": 864, "h": 480, "resolution": "864x480", "humanbitrate": "33Mb/s-159Mb/s", "minbps": 33177600, "maxbps": 159252480, "fps": [24, 20, 15, 10, 8, 5]}, {"w": 960, "h": 720, "resolution": "960x720", "humanbitrate": "55Mb/s-165Mb/s", "minbps": 55296000, "maxbps": 165888000, "fps": [15, 10, 8, 5]}, {"w": 1024, "h": 576, "resolution": "1024x576", "humanbitrate": "47Mb/s-141Mb/s", "minbps": 47185920, "maxbps": 141557760, "fps": [15, 10, 8, 5]}, {"w": 1280, "h": 720, "resolution": "1280x720", "humanbitrate": "73Mb/s-147Mb/s", "minbps": 73728000, "maxbps": 147456000, "fps": [10, 8, 5]}, {"w": 1600, "h": 896, "resolution": "1600x896", "humanbitrate": "114Mb/s-172Mb/s", "minbps": 114688000, "maxbps": 172032000, "fps": [8, 5]}, {"w": 1920, "h": 1080, "resolution": "1920x1080", "humanbitrate": "165Mb/s", "minbps": 165888000, "maxbps": 165888000, "fps": [5]}, {"w": 2304, "h": 1296, "resolution": "2304x1296", "humanbitrate": "238Mb/s", "minbps": 238878720, "maxbps": 238878720, "fps": [2]}, {"w": 2304, "h": 1536, "resolution": "2304x1536", "humanbitrate": "283Mb/s", "minbps": 283115520, "maxbps": 283115520, "fps": [2]}], "name": "FORMAT_UNCOMPRESSED", "fourcc": "YUY2", "bpp": 16}, {"resolutions": [{"w": 640, "h": 480, "resolution": "640x480", "humanbitrate": "24Mb/s-147Mb/s", "minbps": 24576000, "maxbps": 147456000, "fps": [30, 24, 20, 15, 10, 8, 5]}, {"w": 160, "h": 90, "resolution": "160x90", "humanbitrate": "1152Kb/s-6912Kb/s", "minbps": 1152000, "maxbps": 6912000, "fps": [30, 24, 20, 15, 10, 8, 5]}, {"w": 160, "h": 120, "resolution": "160x120", "humanbitrate": "1536Kb/s-9216Kb/s", "minbps": 1536000, "maxbps": 9216000, "fps": [30, 24, 20, 15, 10, 8, 5]}, {"w": 176, "h": 144, "resolution": "176x144", "humanbitrate": "2027Kb/s-12Mb/s", "minbps": 2027520, "maxbps": 12165120, "fps": [30, 24, 20, 15, 10, 8, 5]}, {"w": 320, "h": 180, "resolution": "320x180", "humanbitrate": "4608Kb/s-27Mb/s", "minbps": 4608000, "maxbps": 27648000, "fps": [30, 24, 20, 15, 10, 8, 5]}, {"w": 320, "h": 240, "resolution": "320x240", "humanbitrate": "6144Kb/s-36Mb/s", "minbps": 6144000, "maxbps": 36864000, "fps": [30, 24, 20, 15, 10, 8, 5]}, {"w": 352, "h": 288, "resolution": "352x288", "humanbitrate": "8110Kb/s-48Mb/s", "minbps": 8110080, "maxbps": 48660480, "fps": [30, 24, 20, 15, 10, 8, 5]}, {"w": 432, "h": 240, "resolution": "432x240", "humanbitrate": "8294Kb/s-49Mb/s", "minbps": 8294400, "maxbps": 49766400, "fps": [30, 24, 20, 15, 10, 8, 5]}, {"w": 640, "h": 360, "resolution": "640x360", "humanbitrate": "18Mb/s-110Mb/s", "minbps": 18432000, "maxbps": 110592000, "fps": [30, 24, 20, 15, 10, 8, 5]}, {"w": 800, "h": 448, "resolution": "800x448", "humanbitrate": "28Mb/s-172Mb/s", "minbps": 28672000, "maxbps": 172032000, "fps": [30, 24, 20, 15, 10, 8, 5]}, {"w": 800, "h": 600, "resolution": "800x600", "humanbitrate": "38Mb/s-230Mb/s", "minbps": 38400000, "maxbps": 230400000, "fps": [30, 24, 20, 15, 10, 8, 5]}, {"w": 864, "h": 480, "resolution": "864x480", "humanbitrate": "33Mb/s-199Mb/s", "minbps": 33177600, "maxbps": 199065600, "fps": [30, 24, 20, 15, 10, 8, 5]}, {"w": 960, "h": 720, "resolution": "960x720", "humanbitrate": "55Mb/s-331Mb/s", "minbps": 55296000, "maxbps": 331776000, "fps": [30, 24, 20, 15, 10, 8, 5]}, {"w": 1024, "h": 576, "resolution": "1024x576", "humanbitrate": "47Mb/s-283Mb/s", "minbps": 47185920, "maxbps": 283115520, "fps": [30, 24, 20, 15, 10, 8, 5]}, {"w": 1280, "h": 720, "resolution": "1280x720", "humanbitrate": "73Mb/s-442Mb/s", "minbps": 73728000, "maxbps": 442368000, "fps": [30, 24, 20, 15, 10, 8, 5]}, {"w": 1600, "h": 896, "resolution": "1600x896", "humanbitrate": "114Mb/s-688Mb/s", "minbps": 114688000, "maxbps": 688128000, "fps": [30, 24, 20, 15, 10, 8, 5]}, {"w": 1920, "h": 1080, "resolution": "1920x1080", "humanbitrate": "165Mb/s-995Mb/s", "minbps": 165888000, "maxbps": 995328000, "fps": [30, 24, 20, 15, 10, 8, 5]}], "name": "FORMAT_MJPEG"}], "endpoints": [{"interval": "1", "maxburst": "?", "mult": "?", "packet": "0x00c0  1x 192 bytes", "bitrate": 12288000, "humanbitrate": "12Mb/s"}, {"interval": "1", "maxburst": "?", "mult": "?", "packet": "0x0180  1x 384 bytes", "bitrate": 24576000, "humanbitrate": "24Mb/s"}, {"interval": "1", "maxburst": "?", "mult": "?", "packet": "0x0200  1x 512 bytes", "bitrate": 32768000, "humanbitrate": "32Mb/s"}, {"interval": "1", "maxburst": "?", "mult": "?", "packet": "0x0280  1x 640 bytes", "bitrate": 40960000, "humanbitrate": "40Mb/s"}, {"interval": "1", "maxburst": "?", "mult": "?", "packet": "0x0320  1x 800 bytes", "bitrate": 51200000, "humanbitrate": "51Mb/s"}, {"interval": "1", "maxburst": "?", "mult": "?", "packet": "0x03b0  1x 944 bytes", "bitrate": 60416000, "humanbitrate": "60Mb/s"}, {"interval": "1", "maxburst": "?", "mult": "?", "packet": "0x0a80  2x 640 bytes", "bitrate": 81920000, "humanbitrate": "81Mb/s"}, {"interval": "1", "maxburst": "?", "mult": "?", "packet": "0x0b20  2x 800 bytes", "bitrate": 102400000, "humanbitrate": "102Mb/s"}, {"interval": "1", "maxburst": "?", "mult": "?", "packet": "0x0be0  2x 992 bytes", "bitrate": 126976000, "humanbitrate": "126Mb/s"}, {"interval": "1", "maxburst": "?", "mult": "?", "packet": "0x1380  3x 896 bytes", "bitrate": 172032000, "humanbitrate": "172Mb/s"}, {"interval": "1", "maxburst": "?", "mult": "?", "packet": "0x1400  3x 1024 bytes", "bitrate": 196608000, "humanbitrate": "196Mb/s"}]}